<StartOutput>
    <Paragraphs Count="8">
        <Paragraph id="0">
            <Sentences Count="1">
                <Sentence id="0" offset="0:120">
                    <Text>This spontaneous report from a patient concerns a 71 yo Caucasian female from the United
                        States: Local ID: 1-1878275180.
                    </Text>
                    <Tokens Count="22">
                        <Token POSTag="DT" globalID="0" id="0" offset="0:4">
                            <Text>This</Text>
                        </Token>
                        <Token POSTag="JJ" globalID="1" id="1" offset="5:16">
                            <Text>spontaneous</Text>
                        </Token>
                        <Token POSTag="NN" globalID="2" id="2" offset="17:23">
                            <Text>report</Text>
                        </Token>
                        <Token POSTag="IN" globalID="3" id="3" offset="24:28">
                            <Text>from</Text>
                        </Token>
                        <Token POSTag="DT" globalID="4" id="4" offset="29:30">
                            <Text>a</Text>
                        </Token>
                        <Token POSTag="NN" globalID="5" id="5" offset="31:38">
                            <Text>patient</Text>
                        </Token>
                        <Token POSTag="VBZ" globalID="6" id="6" offset="39:47">
                            <Text>concerns</Text>
                        </Token>
                        <Token POSTag="DT" globalID="7" id="7" offset="48:49">
                            <Text>a</Text>
                        </Token>
                        <Token POSTag="CD" globalID="8" id="8" offset="50:52">
                            <Text>71</Text>
                        </Token>
                        <Token POSTag="NN" globalID="9" id="9" offset="53:55">
                            <Text>yo</Text>
                        </Token>
                        <Token POSTag="NN" globalID="10" id="10" offset="56:65">
                            <Text>Caucasian</Text>
                        </Token>
                        <Token POSTag="NN" globalID="11" id="11" offset="66:72">
                            <Text>female</Text>
                        </Token>
                        <Token POSTag="IN" globalID="12" id="12" offset="73:77">
                            <Text>from</Text>
                        </Token>
                        <Token POSTag="DT" globalID="13" id="13" offset="78:81">
                            <Text>the</Text>
                        </Token>
                        <Token POSTag="JJ" globalID="14" id="14" offset="82:88">
                            <Text>United</Text>
                        </Token>
                        <Token POSTag="NNS" globalID="15" id="15" offset="89:95">
                            <Text>States</Text>
                        </Token>
                        <Token POSTag=":" globalID="16" id="16" offset="95:96">
                            <Text>:</Text>
                        </Token>
                        <Token POSTag="JJ" globalID="17" id="17" offset="97:102">
                            <Text>Local</Text>
                        </Token>
                        <Token POSTag="NN" globalID="18" id="18" offset="103:105">
                            <Text>ID</Text>
                        </Token>
                        <Token POSTag=":" globalID="19" id="19" offset="105:106">
                            <Text>:</Text>
                        </Token>
                        <Token POSTag="CD" globalID="20" id="20" offset="107:119">
                            <Text>1-1878275180</Text>
                        </Token>
                        <Token POSTag="." globalID="21" id="21" offset="119:120">
                            <Text>.</Text>
                        </Token>
                    </Tokens>
                    <ParseTree/>
                </Sentence>
            </Sentences>
        </Paragraph>
        <Paragraph id="1">
            <Sentences Count="0"/>
        </Paragraph>
        <Paragraph id="2">
            <Sentences Count="9">
                <Sentence id="0" offset="122:185">
                    <Text>The patient's weight was 160 pounds and height was 67.5 inches.</Text>
                    <Tokens Count="13">
                        <Token POSTag="DT" globalID="22" id="0" offset="122:125">
                            <Text>The</Text>
                        </Token>
                        <Token POSTag="NN" globalID="23" id="1" offset="126:133">
                            <Text>patient</Text>
                        </Token>
                        <Token POSTag="POS" globalID="24" id="2" offset="133:135">
                            <Text>'s</Text>
                        </Token>
                        <Token POSTag="NN" globalID="25" id="3" offset="136:142">
                            <Text>weight</Text>
                        </Token>
                        <Token POSTag="VBD" globalID="26" id="4" offset="143:146">
                            <Text>was</Text>
                        </Token>
                        <Token POSTag="CD" globalID="27" id="5" offset="147:150">
                            <Text>160</Text>
                        </Token>
                        <Token POSTag="NNS" globalID="28" id="6" offset="151:157">
                            <Text>pounds</Text>
                        </Token>
                        <Token POSTag="CC" globalID="29" id="7" offset="158:161">
                            <Text>and</Text>
                        </Token>
                        <Token POSTag="NN" globalID="30" id="8" offset="162:168">
                            <Text>height</Text>
                        </Token>
                        <Token POSTag="VBD" globalID="31" id="9" offset="169:172">
                            <Text>was</Text>
                        </Token>
                        <Token POSTag="CD" globalID="32" id="10" offset="173:177">
                            <Text>67.5</Text>
                        </Token>
                        <Token POSTag="NNS" globalID="33" id="11" offset="178:184">
                            <Text>inches</Text>
                        </Token>
                        <Token POSTag="." globalID="34" id="12" offset="184:185">
                            <Text>.</Text>
                        </Token>
                    </Tokens>
                    <ParseTree/>
                </Sentence>
                <Sentence id="1" offset="187:273">
                    <Text>Concurrent conditions included abdominal bloating, abdominal gas, and type 2 diabetes.</Text>
                    <Tokens Count="14">
                        <Token POSTag="JJ" globalID="35" id="0" offset="187:197">
                            <Text>Concurrent</Text>
                        </Token>
                        <Token POSTag="NNS" globalID="36" id="1" offset="198:208">
                            <Text>conditions</Text>
                        </Token>
                        <Token POSTag="VBD" globalID="37" id="2" offset="209:217">
                            <Text>included</Text>
                        </Token>
                        <Token POSTag="JJ" globalID="38" id="3" offset="218:227">
                            <Text>abdominal</Text>
                        </Token>
                        <Token POSTag="NN" globalID="39" id="4" offset="228:236">
                            <Text>bloating</Text>
                        </Token>
                        <Token POSTag="," globalID="40" id="5" offset="236:237">
                            <Text>,</Text>
                        </Token>
                        <Token POSTag="JJ" globalID="41" id="6" offset="238:247">
                            <Text>abdominal</Text>
                        </Token>
                        <Token POSTag="NN" globalID="42" id="7" offset="248:251">
                            <Text>gas</Text>
                        </Token>
                        <Token POSTag="," globalID="43" id="8" offset="251:252">
                            <Text>,</Text>
                        </Token>
                        <Token POSTag="CC" globalID="44" id="9" offset="253:256">
                            <Text>and</Text>
                        </Token>
                        <Token POSTag="NN" globalID="45" id="10" offset="257:261">
                            <Text>type</Text>
                        </Token>
                        <Token POSTag="CD" globalID="46" id="11" offset="262:263">
                            <Text>2</Text>
                        </Token>
                        <Token POSTag="NNS" globalID="47" id="12" offset="264:272">
                            <Text>diabetes</Text>
                        </Token>
                        <Token POSTag="." globalID="48" id="13" offset="272:273">
                            <Text>.</Text>
                        </Token>
                    </Tokens>
                    <ParseTree/>
                </Sentence>
                <Sentence id="2" offset="275:348">
                    <Text>Other medical history included no history of drug abuse/illicit drug use.</Text>
                    <Tokens Count="12">
                        <Token POSTag="JJ" globalID="49" id="0" offset="275:280">
                            <Text>Other</Text>
                        </Token>
                        <Token POSTag="JJ" globalID="50" id="1" offset="281:288">
                            <Text>medical</Text>
                        </Token>
                        <Token POSTag="NN" globalID="51" id="2" offset="289:296">
                            <Text>history</Text>
                        </Token>
                        <Token POSTag="VBD" globalID="52" id="3" offset="297:305">
                            <Text>included</Text>
                        </Token>
                        <Token POSTag="DT" globalID="53" id="4" offset="306:308">
                            <Text>no</Text>
                        </Token>
                        <Token POSTag="NN" globalID="54" id="5" offset="309:316">
                            <Text>history</Text>
                        </Token>
                        <Token POSTag="IN" globalID="55" id="6" offset="317:319">
                            <Text>of</Text>
                        </Token>
                        <Token POSTag="NN" globalID="56" id="7" offset="320:324">
                            <Text>drug</Text>
                        </Token>
                        <Token POSTag="NN" globalID="57" id="8" offset="325:338">
                            <Text>abuse/illicit</Text>
                        </Token>
                        <Token POSTag="NN" globalID="58" id="9" offset="339:343">
                            <Text>drug</Text>
                        </Token>
                        <Token POSTag="NN" globalID="59" id="10" offset="344:347">
                            <Text>use</Text>
                        </Token>
                        <Token POSTag="." globalID="60" id="11" offset="347:348">
                            <Text>.</Text>
                        </Token>
                    </Tokens>
                    <ParseTree/>
                </Sentence>
                <Sentence id="3" offset="349:592">
                    <Text>The patient was treated with canagliflozin (tablet, oral, batch unknown) 300 mg once a day,
                        initiated on 06-AUG-2014, for type 2 diabetes In AUG-2014, the patient contacted her physician
                        about the events and was prescribed an increased dosage.
                    </Text>
                    <Tokens Count="46">
                        <Token POSTag="DT" globalID="61" id="0" offset="349:352">
                            <Text>The</Text>
                        </Token>
                        <Token POSTag="NN" globalID="62" id="1" offset="353:360">
                            <Text>patient</Text>
                        </Token>
                        <Token POSTag="VBD" globalID="63" id="2" offset="361:364">
                            <Text>was</Text>
                        </Token>
                        <Token POSTag="VBN" globalID="64" id="3" offset="365:372">
                            <Text>treated</Text>
                        </Token>
                        <Token POSTag="IN" globalID="65" id="4" offset="373:377">
                            <Text>with</Text>
                        </Token>
                        <Token POSTag="NN" globalID="66" id="5" offset="378:391">
                            <Text>canagliflozin</Text>
                        </Token>
                        <Token POSTag="-LRB-" globalID="67" id="6" offset="392:393">
                            <Text>(</Text>
                        </Token>
                        <Token POSTag="NN" globalID="68" id="7" offset="393:399">
                            <Text>tablet</Text>
                        </Token>
                        <Token POSTag="," globalID="69" id="8" offset="399:400">
                            <Text>,</Text>
                        </Token>
                        <Token POSTag="JJ" globalID="70" id="9" offset="401:405">
                            <Text>oral</Text>
                        </Token>
                        <Token POSTag="," globalID="71" id="10" offset="405:406">
                            <Text>,</Text>
                        </Token>
                        <Token POSTag="JJ" globalID="72" id="11" offset="407:412">
                            <Text>batch</Text>
                        </Token>
                        <Token POSTag="JJ" globalID="73" id="12" offset="413:420">
                            <Text>unknown</Text>
                        </Token>
                        <Token POSTag="-RRB-" globalID="74" id="13" offset="420:421">
                            <Text>)</Text>
                        </Token>
                        <Token POSTag="CD" globalID="75" id="14" offset="422:425">
                            <Text>300</Text>
                        </Token>
                        <Token POSTag="NN" globalID="76" id="15" offset="426:428">
                            <Text>mg</Text>
                        </Token>
                        <Token POSTag="IN" globalID="77" id="16" offset="429:433">
                            <Text>once</Text>
                        </Token>
                        <Token POSTag="DT" globalID="78" id="17" offset="434:435">
                            <Text>a</Text>
                        </Token>
                        <Token POSTag="NN" globalID="79" id="18" offset="436:439">
                            <Text>day</Text>
                        </Token>
                        <Token POSTag="," globalID="80" id="19" offset="439:440">
                            <Text>,</Text>
                        </Token>
                        <Token POSTag="VBN" globalID="81" id="20" offset="441:450">
                            <Text>initiated</Text>
                        </Token>
                        <Token POSTag="IN" globalID="82" id="21" offset="451:453">
                            <Text>on</Text>
                        </Token>
                        <Token POSTag="NN" globalID="83" id="22" offset="454:465">
                            <Text>06-AUG-2014</Text>
                        </Token>
                        <Token POSTag="," globalID="84" id="23" offset="465:466">
                            <Text>,</Text>
                        </Token>
                        <Token POSTag="IN" globalID="85" id="24" offset="467:470">
                            <Text>for</Text>
                        </Token>
                        <Token POSTag="NN" globalID="86" id="25" offset="471:475">
                            <Text>type</Text>
                        </Token>
                        <Token POSTag="CD" globalID="87" id="26" offset="476:477">
                            <Text>2</Text>
                        </Token>
                        <Token POSTag="NNS" globalID="88" id="27" offset="478:486">
                            <Text>diabetes</Text>
                        </Token>
                        <Token POSTag="IN" globalID="89" id="28" offset="487:489">
                            <Text>In</Text>
                        </Token>
                        <Token POSTag="NN" globalID="90" id="29" offset="490:498">
                            <Text>AUG-2014</Text>
                        </Token>
                        <Token POSTag="," globalID="91" id="30" offset="498:499">
                            <Text>,</Text>
                        </Token>
                        <Token POSTag="DT" globalID="92" id="31" offset="500:503">
                            <Text>the</Text>
                        </Token>
                        <Token POSTag="NN" globalID="93" id="32" offset="504:511">
                            <Text>patient</Text>
                        </Token>
                        <Token POSTag="VBD" globalID="94" id="33" offset="512:521">
                            <Text>contacted</Text>
                        </Token>
                        <Token POSTag="PRP$" globalID="95" id="34" offset="522:525">
                            <Text>her</Text>
                        </Token>
                        <Token POSTag="NN" globalID="96" id="35" offset="526:535">
                            <Text>physician</Text>
                        </Token>
                        <Token POSTag="IN" globalID="97" id="36" offset="536:541">
                            <Text>about</Text>
                        </Token>
                        <Token POSTag="DT" globalID="98" id="37" offset="542:545">
                            <Text>the</Text>
                        </Token>
                        <Token POSTag="NNS" globalID="99" id="38" offset="546:552">
                            <Text>events</Text>
                        </Token>
                        <Token POSTag="CC" globalID="100" id="39" offset="553:556">
                            <Text>and</Text>
                        </Token>
                        <Token POSTag="VBD" globalID="101" id="40" offset="557:560">
                            <Text>was</Text>
                        </Token>
                        <Token POSTag="VBN" globalID="102" id="41" offset="561:571">
                            <Text>prescribed</Text>
                        </Token>
                        <Token POSTag="DT" globalID="103" id="42" offset="572:574">
                            <Text>an</Text>
                        </Token>
                        <Token POSTag="VBN" globalID="104" id="43" offset="575:584">
                            <Text>increased</Text>
                        </Token>
                        <Token POSTag="NN" globalID="105" id="44" offset="585:591">
                            <Text>dosage</Text>
                        </Token>
                        <Token POSTag="." globalID="106" id="45" offset="591:592">
                            <Text>.</Text>
                        </Token>
                    </Tokens>
                    <ParseTree/>
                </Sentence>
                <Sentence id="4" offset="594:689">
                    <Text>The patient reported the increased dose of domperidone had not relieved her worsening
                        symptoms.
                    </Text>
                    <Tokens Count="15">
                        <Token POSTag="DT" globalID="107" id="0" offset="594:597">
                            <Text>The</Text>
                        </Token>
                        <Token POSTag="NN" globalID="108" id="1" offset="598:605">
                            <Text>patient</Text>
                        </Token>
                        <Token POSTag="VBD" globalID="109" id="2" offset="606:614">
                            <Text>reported</Text>
                        </Token>
                        <Token POSTag="DT" globalID="110" id="3" offset="615:618">
                            <Text>the</Text>
                        </Token>
                        <Token POSTag="VBN" globalID="111" id="4" offset="619:628">
                            <Text>increased</Text>
                        </Token>
                        <Token POSTag="NN" globalID="112" id="5" offset="629:633">
                            <Text>dose</Text>
                        </Token>
                        <Token POSTag="IN" globalID="113" id="6" offset="634:636">
                            <Text>of</Text>
                        </Token>
                        <Token POSTag="NN" globalID="114" id="7" offset="637:648">
                            <Text>domperidone</Text>
                        </Token>
                        <Token POSTag="VBD" globalID="115" id="8" offset="649:652">
                            <Text>had</Text>
                        </Token>
                        <Token POSTag="RB" globalID="116" id="9" offset="653:656">
                            <Text>not</Text>
                        </Token>
                        <Token POSTag="VBN" globalID="117" id="10" offset="657:665">
                            <Text>relieved</Text>
                        </Token>
                        <Token POSTag="PRP$" globalID="118" id="11" offset="666:669">
                            <Text>her</Text>
                        </Token>
                        <Token POSTag="JJ" globalID="119" id="12" offset="670:679">
                            <Text>worsening</Text>
                        </Token>
                        <Token POSTag="NNS" globalID="120" id="13" offset="680:688">
                            <Text>symptoms</Text>
                        </Token>
                        <Token POSTag="." globalID="121" id="14" offset="688:689">
                            <Text>.</Text>
                        </Token>
                    </Tokens>
                    <ParseTree/>
                </Sentence>
                <Sentence id="5" offset="691:754">
                    <Text>On 13-AUG-2014, the patient experienced not feeling well today.</Text>
                    <Tokens Count="11">
                        <Token POSTag="IN" globalID="122" id="0" offset="691:693">
                            <Text>On</Text>
                        </Token>
                        <Token POSTag="NN" globalID="123" id="1" offset="694:705">
                            <Text>13-AUG-2014</Text>
                        </Token>
                        <Token POSTag="," globalID="124" id="2" offset="705:706">
                            <Text>,</Text>
                        </Token>
                        <Token POSTag="DT" globalID="125" id="3" offset="707:710">
                            <Text>the</Text>
                        </Token>
                        <Token POSTag="NN" globalID="126" id="4" offset="711:718">
                            <Text>patient</Text>
                        </Token>
                        <Token POSTag="VBN" globalID="127" id="5" offset="719:730">
                            <Text>experienced</Text>
                        </Token>
                        <Token POSTag="RB" globalID="128" id="6" offset="731:734">
                            <Text>not</Text>
                        </Token>
                        <Token POSTag="NN" globalID="129" id="7" offset="735:742">
                            <Text>feeling</Text>
                        </Token>
                        <Token POSTag="RB" globalID="130" id="8" offset="743:747">
                            <Text>well</Text>
                        </Token>
                        <Token POSTag="RB" globalID="131" id="9" offset="748:753">
                            <Text>today</Text>
                        </Token>
                        <Token POSTag="." globalID="132" id="10" offset="753:754">
                            <Text>.</Text>
                        </Token>
                    </Tokens>
                    <ParseTree/>
                </Sentence>
                <Sentence id="6" offset="756:793">
                    <Text>No laboratory findings were provided.</Text>
                    <Tokens Count="6">
                        <Token POSTag="NN" globalID="133" id="0" offset="756:758">
                            <Text>No</Text>
                        </Token>
                        <Token POSTag="NN" globalID="134" id="1" offset="759:769">
                            <Text>laboratory</Text>
                        </Token>
                        <Token POSTag="NNS" globalID="135" id="2" offset="770:778">
                            <Text>findings</Text>
                        </Token>
                        <Token POSTag="VBD" globalID="136" id="3" offset="779:783">
                            <Text>were</Text>
                        </Token>
                        <Token POSTag="VBN" globalID="137" id="4" offset="784:792">
                            <Text>provided</Text>
                        </Token>
                        <Token POSTag="." globalID="138" id="5" offset="792:793">
                            <Text>.</Text>
                        </Token>
                    </Tokens>
                    <ParseTree/>
                </Sentence>
                <Sentence id="7" offset="795:879">
                    <Text>The dose of domperidone was increased and the dose of canagliflozin was not changed.</Text>
                    <Tokens Count="15">
                        <Token POSTag="DT" globalID="139" id="0" offset="795:798">
                            <Text>The</Text>
                        </Token>
                        <Token POSTag="NN" globalID="140" id="1" offset="799:803">
                            <Text>dose</Text>
                        </Token>
                        <Token POSTag="IN" globalID="141" id="2" offset="804:806">
                            <Text>of</Text>
                        </Token>
                        <Token POSTag="NN" globalID="142" id="3" offset="807:818">
                            <Text>domperidone</Text>
                        </Token>
                        <Token POSTag="VBD" globalID="143" id="4" offset="819:822">
                            <Text>was</Text>
                        </Token>
                        <Token POSTag="VBN" globalID="144" id="5" offset="823:832">
                            <Text>increased</Text>
                        </Token>
                        <Token POSTag="CC" globalID="145" id="6" offset="833:836">
                            <Text>and</Text>
                        </Token>
                        <Token POSTag="DT" globalID="146" id="7" offset="837:840">
                            <Text>the</Text>
                        </Token>
                        <Token POSTag="NN" globalID="147" id="8" offset="841:845">
                            <Text>dose</Text>
                        </Token>
                        <Token POSTag="IN" globalID="148" id="9" offset="846:848">
                            <Text>of</Text>
                        </Token>
                        <Token POSTag="NN" globalID="149" id="10" offset="849:862">
                            <Text>canagliflozin</Text>
                        </Token>
                        <Token POSTag="VBD" globalID="150" id="11" offset="863:866">
                            <Text>was</Text>
                        </Token>
                        <Token POSTag="RB" globalID="151" id="12" offset="867:870">
                            <Text>not</Text>
                        </Token>
                        <Token POSTag="VBN" globalID="152" id="13" offset="871:878">
                            <Text>changed</Text>
                        </Token>
                        <Token POSTag="." globalID="153" id="14" offset="878:879">
                            <Text>.</Text>
                        </Token>
                    </Tokens>
                    <ParseTree/>
                </Sentence>
                <Sentence id="8" offset="881:1030">
                    <Text>The patient had not recovered from increased belching, worsening of abdominal pain, very
                        gaseous, worsening of bloating, and not feeling well today.
                    </Text>
                    <Tokens Count="27">
                        <Token POSTag="DT" globalID="154" id="0" offset="881:884">
                            <Text>The</Text>
                        </Token>
                        <Token POSTag="NN" globalID="155" id="1" offset="885:892">
                            <Text>patient</Text>
                        </Token>
                        <Token POSTag="VBD" globalID="156" id="2" offset="893:896">
                            <Text>had</Text>
                        </Token>
                        <Token POSTag="RB" globalID="157" id="3" offset="897:900">
                            <Text>not</Text>
                        </Token>
                        <Token POSTag="VBN" globalID="158" id="4" offset="901:910">
                            <Text>recovered</Text>
                        </Token>
                        <Token POSTag="IN" globalID="159" id="5" offset="911:915">
                            <Text>from</Text>
                        </Token>
                        <Token POSTag="VBN" globalID="160" id="6" offset="916:925">
                            <Text>increased</Text>
                        </Token>
                        <Token POSTag="JJ" globalID="161" id="7" offset="926:934">
                            <Text>belching</Text>
                        </Token>
                        <Token POSTag="," globalID="162" id="8" offset="934:935">
                            <Text>,</Text>
                        </Token>
                        <Token POSTag="NN" globalID="163" id="9" offset="936:945">
                            <Text>worsening</Text>
                        </Token>
                        <Token POSTag="IN" globalID="164" id="10" offset="946:948">
                            <Text>of</Text>
                        </Token>
                        <Token POSTag="JJ" globalID="165" id="11" offset="949:958">
                            <Text>abdominal</Text>
                        </Token>
                        <Token POSTag="NN" globalID="166" id="12" offset="959:963">
                            <Text>pain</Text>
                        </Token>
                        <Token POSTag="," globalID="167" id="13" offset="963:964">
                            <Text>,</Text>
                        </Token>
                        <Token POSTag="RB" globalID="168" id="14" offset="965:969">
                            <Text>very</Text>
                        </Token>
                        <Token POSTag="JJ" globalID="169" id="15" offset="970:977">
                            <Text>gaseous</Text>
                        </Token>
                        <Token POSTag="," globalID="170" id="16" offset="977:978">
                            <Text>,</Text>
                        </Token>
                        <Token POSTag="JJ" globalID="171" id="17" offset="979:988">
                            <Text>worsening</Text>
                        </Token>
                        <Token POSTag="IN" globalID="172" id="18" offset="989:991">
                            <Text>of</Text>
                        </Token>
                        <Token POSTag="NN" globalID="173" id="19" offset="992:1000">
                            <Text>bloating</Text>
                        </Token>
                        <Token POSTag="," globalID="174" id="20" offset="1000:1001">
                            <Text>,</Text>
                        </Token>
                        <Token POSTag="CC" globalID="175" id="21" offset="1002:1005">
                            <Text>and</Text>
                        </Token>
                        <Token POSTag="RB" globalID="176" id="22" offset="1006:1009">
                            <Text>not</Text>
                        </Token>
                        <Token POSTag="JJ" globalID="177" id="23" offset="1010:1017">
                            <Text>feeling</Text>
                        </Token>
                        <Token POSTag="NN" globalID="178" id="24" offset="1018:1022">
                            <Text>well</Text>
                        </Token>
                        <Token POSTag="NN" globalID="179" id="25" offset="1023:1028">
                            <Text>today</Text>
                        </Token>
                        <Token POSTag="." globalID="180" id="26" offset="1028:1029">
                            <Text>.</Text>
                        </Token>
                    </Tokens>
                    <ParseTree/>
                </Sentence>
            </Sentences>
        </Paragraph>
        <Paragraph id="3">
            <Sentences Count="0"/>
        </Paragraph>
        <Paragraph id="4">
            <Sentences Count="1">
                <Sentence id="0" offset="1032:1145">
                    <Text>This report was identified by the call center as a product quality complaint: PQMS reference
                        number 10000228235.
                    </Text>
                    <Tokens Count="19">
                        <Token POSTag="DT" globalID="181" id="0" offset="1032:1036">
                            <Text>This</Text>
                        </Token>
                        <Token POSTag="NN" globalID="182" id="1" offset="1037:1043">
                            <Text>report</Text>
                        </Token>
                        <Token POSTag="VBD" globalID="183" id="2" offset="1044:1047">
                            <Text>was</Text>
                        </Token>
                        <Token POSTag="VBN" globalID="184" id="3" offset="1048:1058">
                            <Text>identified</Text>
                        </Token>
                        <Token POSTag="IN" globalID="185" id="4" offset="1059:1061">
                            <Text>by</Text>
                        </Token>
                        <Token POSTag="DT" globalID="186" id="5" offset="1062:1065">
                            <Text>the</Text>
                        </Token>
                        <Token POSTag="NN" globalID="187" id="6" offset="1066:1070">
                            <Text>call</Text>
                        </Token>
                        <Token POSTag="NN" globalID="188" id="7" offset="1071:1077">
                            <Text>center</Text>
                        </Token>
                        <Token POSTag="IN" globalID="189" id="8" offset="1078:1080">
                            <Text>as</Text>
                        </Token>
                        <Token POSTag="DT" globalID="190" id="9" offset="1078:1079">
                            <Text>a</Text>
                        </Token>
                        <Token POSTag="NN" globalID="191" id="10" offset="1083:1090">
                            <Text>product</Text>
                        </Token>
                        <Token POSTag="NN" globalID="192" id="11" offset="1091:1098">
                            <Text>quality</Text>
                        </Token>
                        <Token POSTag="NN" globalID="193" id="12" offset="1099:1108">
                            <Text>complaint</Text>
                        </Token>
                        <Token POSTag=":" globalID="194" id="13" offset="1108:1109">
                            <Text>:</Text>
                        </Token>
                        <Token POSTag="NN" globalID="195" id="14" offset="1111:1115">
                            <Text>PQMS</Text>
                        </Token>
                        <Token POSTag="NN" globalID="196" id="15" offset="1116:1125">
                            <Text>reference</Text>
                        </Token>
                        <Token POSTag="NN" globalID="197" id="16" offset="1126:1132">
                            <Text>number</Text>
                        </Token>
                        <Token POSTag="CD" globalID="198" id="17" offset="1133:1144">
                            <Text>10000228235</Text>
                        </Token>
                        <Token POSTag="." globalID="199" id="18" offset="1144:1145">
                            <Text>.</Text>
                        </Token>
                    </Tokens>
                    <ParseTree/>
                </Sentence>
            </Sentences>
        </Paragraph>
        <Paragraph id="5">
            <Sentences Count="0"/>
        </Paragraph>
        <Paragraph id="6">
            <Sentences Count="1">
                <Sentence id="0" offset="1147:1175">
                    <Text>This report was not serious.</Text>
                    <Tokens Count="6">
                        <Token POSTag="DT" globalID="200" id="0" offset="1147:1151">
                            <Text>This</Text>
                        </Token>
                        <Token POSTag="NN" globalID="201" id="1" offset="1152:1158">
                            <Text>report</Text>
                        </Token>
                        <Token POSTag="VBD" globalID="202" id="2" offset="1159:1162">
                            <Text>was</Text>
                        </Token>
                        <Token POSTag="RB" globalID="203" id="3" offset="1163:1166">
                            <Text>not</Text>
                        </Token>
                        <Token POSTag="JJ" globalID="204" id="4" offset="1167:1174">
                            <Text>serious</Text>
                        </Token>
                        <Token POSTag="." globalID="205" id="5" offset="1174:1175">
                            <Text>.</Text>
                        </Token>
                    </Tokens>
                    <ParseTree/>
                </Sentence>
            </Sentences>
        </Paragraph>
        <Paragraph id="7">
            <Sentences Count="0"/>
        </Paragraph>
    </Paragraphs>
</StartOutput>