<StartOutput>
    <Paragraphs Count="12">
        <Paragraph id="0">
            <Sentences Count="2">
                <Sentence id="0" offset="0:158">
                    <Text>16-Apr-2015, non health professional reported the case of a Female patient (age 60, 140lbs)
                        who received ERYTHROMYCIN (Product be excluded as a Teva product).
                    </Text>
                    <Tokens Count="31">
                        <Token POSTag="CD" globalID="0" id="0" offset="0:11">
                            <Text>16-Apr-2015</Text>
                        </Token>
                        <Token POSTag="," globalID="1" id="1" offset="11:12">
                            <Text>,</Text>
                        </Token>
                        <Token POSTag="JJ" globalID="2" id="2" offset="13:16">
                            <Text>non</Text>
                        </Token>
                        <Token POSTag="NN" globalID="3" id="3" offset="17:23">
                            <Text>health</Text>
                        </Token>
                        <Token POSTag="NN" globalID="4" id="4" offset="24:36">
                            <Text>professional</Text>
                        </Token>
                        <Token POSTag="VBD" globalID="5" id="5" offset="37:45">
                            <Text>reported</Text>
                        </Token>
                        <Token POSTag="DT" globalID="6" id="6" offset="46:49">
                            <Text>the</Text>
                        </Token>
                        <Token POSTag="NN" globalID="7" id="7" offset="50:54">
                            <Text>case</Text>
                        </Token>
                        <Token POSTag="IN" globalID="8" id="8" offset="55:57">
                            <Text>of</Text>
                        </Token>
                        <Token POSTag="DT" globalID="9" id="9" offset="58:59">
                            <Text>a</Text>
                        </Token>
                        <Token POSTag="JJ" globalID="10" id="10" offset="60:66">
                            <Text>Female</Text>
                        </Token>
                        <Token POSTag="NN" globalID="11" id="11" offset="67:74">
                            <Text>patient</Text>
                        </Token>
                        <Token POSTag="-LRB-" globalID="12" id="12" offset="75:76">
                            <Text>(</Text>
                        </Token>
                        <Token POSTag="NN" globalID="13" id="13" offset="76:79">
                            <Text>age</Text>
                        </Token>
                        <Token POSTag="CD" globalID="14" id="14" offset="80:82">
                            <Text>60</Text>
                        </Token>
                        <Token POSTag="," globalID="15" id="15" offset="82:83">
                            <Text>,</Text>
                        </Token>
                        <Token POSTag="NN" globalID="16" id="16" offset="84:90">
                            <Text>140lbs</Text>
                        </Token>
                        <Token POSTag="-RRB-" globalID="17" id="17" offset="90:91">
                            <Text>)</Text>
                        </Token>
                        <Token POSTag="WP" globalID="18" id="18" offset="92:95">
                            <Text>who</Text>
                        </Token>
                        <Token POSTag="VBD" globalID="19" id="19" offset="96:104">
                            <Text>received</Text>
                        </Token>
                        <Token POSTag="NN" globalID="20" id="20" offset="105:117">
                            <Text>ERYTHROMYCIN</Text>
                        </Token>
                        <Token POSTag="-LRB-" globalID="21" id="21" offset="118:119">
                            <Text>(</Text>
                        </Token>
                        <Token POSTag="NN" globalID="22" id="22" offset="119:126">
                            <Text>Product</Text>
                        </Token>
                        <Token POSTag="VB" globalID="23" id="23" offset="127:129">
                            <Text>be</Text>
                        </Token>
                        <Token POSTag="VBN" globalID="24" id="24" offset="130:138">
                            <Text>excluded</Text>
                        </Token>
                        <Token POSTag="IN" globalID="25" id="25" offset="139:141">
                            <Text>as</Text>
                        </Token>
                        <Token POSTag="DT" globalID="26" id="26" offset="139:140">
                            <Text>a</Text>
                        </Token>
                        <Token POSTag="NN" globalID="27" id="27" offset="144:148">
                            <Text>Teva</Text>
                        </Token>
                        <Token POSTag="NN" globalID="28" id="28" offset="149:156">
                            <Text>product</Text>
                        </Token>
                        <Token POSTag="-RRB-" globalID="29" id="29" offset="156:157">
                            <Text>)</Text>
                        </Token>
                        <Token POSTag="." globalID="30" id="30" offset="157:158">
                            <Text>.</Text>
                        </Token>
                    </Tokens>
                    <ParseTree>(S1 (S (S (NP (NP (CD 16-Apr-2015)) (, ,) (NP (JJ non) (NN health) (NN professional)))
                        (VP (VBD reported) (NP (NP (DT the) (NN case)) (PP (IN of) (NP (NP (NP (DT a) (JJ Female) (NN
                        patient)) (PRN (-LRB- -LRB-) (NP (NP (NN age) (CD 60)) (, ,) (NP (NN 140lbs))) (-RRB- -RRB-)))
                        (SBAR (WHNP (WP who)) (S (VP (VBD received) (NP (NP (NN ERYTHROMYCIN)) (PRN (-LRB- -LRB-) (S (NP
                        (NN Product)) (VP (VB be) (VP (VBN excluded) (PP (IN as) (NP (DT a) (NN Teva) (NN product))))))
                        (-RRB- -RRB-))))))))))) (. .)))
                    </ParseTree>
                </Sentence>
                <Sentence id="1" offset="159:275">
                    <Text>While on the suspect medication(s), the patient experienced ARRHYTHMIA(Serious); POSSIBLE DRUG
                        INTERACTION(Serious).
                    </Text>
                    <Tokens Count="24">
                        <Token POSTag="IN" globalID="31" id="0" offset="159:164">
                            <Text>While</Text>
                        </Token>
                        <Token POSTag="IN" globalID="32" id="1" offset="165:167">
                            <Text>on</Text>
                        </Token>
                        <Token POSTag="DT" globalID="33" id="2" offset="168:171">
                            <Text>the</Text>
                        </Token>
                        <Token POSTag="NN" globalID="34" id="3" offset="172:179">
                            <Text>suspect</Text>
                        </Token>
                        <Token POSTag="NN" globalID="35" id="4" offset="180:190">
                            <Text>medication</Text>
                            <METAMAP>[phsu]</METAMAP>
                        </Token>
                        <Token POSTag="-LRB-" globalID="36" id="5" offset="190:191">
                            <Text>(</Text>
                        </Token>
                        <Token POSTag="NNS" globalID="37" id="6" offset="191:192">
                            <Text>s</Text>
                        </Token>
                        <Token POSTag="-RRB-" globalID="38" id="7" offset="192:193">
                            <Text>)</Text>
                        </Token>
                        <Token POSTag="," globalID="39" id="8" offset="193:194">
                            <Text>,</Text>
                        </Token>
                        <Token POSTag="DT" globalID="40" id="9" offset="195:198">
                            <Text>the</Text>
                        </Token>
                        <Token POSTag="NN" globalID="41" id="10" offset="199:206">
                            <Text>patient</Text>
                        </Token>
                        <Token POSTag="VBN" globalID="42" id="11" offset="207:218">
                            <Text>experienced</Text>
                        </Token>
                        <Token POSTag="NN" globalID="43" id="12" offset="219:229">
                            <Text>ARRHYTHMIA</Text>
                        </Token>
                        <Token POSTag="-LRB-" globalID="44" id="13" offset="229:230">
                            <Text>(</Text>
                        </Token>
                        <Token POSTag="JJ" globalID="45" id="14" offset="230:237">
                            <Text>Serious</Text>
                        </Token>
                        <Token POSTag="-RRB-" globalID="46" id="15" offset="237:238">
                            <Text>)</Text>
                        </Token>
                        <Token POSTag=":" globalID="47" id="16" offset="238:239">
                            <Text>;</Text>
                        </Token>
                        <Token POSTag="JJ" globalID="48" id="17" offset="240:248">
                            <Text>POSSIBLE</Text>
                        </Token>
                        <Token POSTag="NN" globalID="49" id="18" offset="249:253">
                            <Text>DRUG</Text>
                        </Token>
                        <Token POSTag="NN" globalID="50" id="19" offset="254:265">
                            <Text>INTERACTION</Text>
                        </Token>
                        <Token POSTag="-LRB-" globalID="51" id="20" offset="265:266">
                            <Text>(</Text>
                        </Token>
                        <Token POSTag="JJ" globalID="52" id="21" offset="266:273">
                            <Text>Serious</Text>
                        </Token>
                        <Token POSTag="-RRB-" globalID="53" id="22" offset="273:274">
                            <Text>)</Text>
                        </Token>
                        <Token POSTag="." globalID="54" id="23" offset="274:275">
                            <Text>.</Text>
                        </Token>
                    </Tokens>
                    <ParseTree>(S1 (S (S (PP (IN While) (PP (IN on) (NP (NP (DT the) (NN suspect) (NN medication)) (PRN
                        (-LRB- -LRB-) (NP (NNS s)) (-RRB- -RRB-))))) (, ,) (NP (DT the) (NN patient)) (VP (VBN
                        experienced) (NP (NP (NN ARRHYTHMIA)) (PRN (-LRB- -LRB-) (NP (JJ Serious)) (-RRB- -RRB-)))) (:
                        ;) (NP (NP (JJ POSSIBLE) (NN DRUG) (NN INTERACTION)) (PRN (-LRB- -LRB-) (NP (JJ Serious)) (-RRB-
                        -RRB-)))) (. .)))
                    </ParseTree>
                </Sentence>
            </Sentences>
        </Paragraph>
        <Paragraph id="1">
            <Sentences Count="0"/>
        </Paragraph>
        <Paragraph id="2">
            <Sentences Count="1">
                <Sentence id="0" offset="277:375">
                    <Text>The patient had medical history of CROHN'S DISEASE(Not Continuing), GASTROPARESIS(Not
                        Continuing).
                    </Text>
                    <Tokens Count="19">
                        <Token POSTag="DT" globalID="55" id="0" offset="277:280">
                            <Text>The</Text>
                        </Token>
                        <Token POSTag="NN" globalID="56" id="1" offset="281:288">
                            <Text>patient</Text>
                        </Token>
                        <Token POSTag="VBD" globalID="57" id="2" offset="289:292">
                            <Text>had</Text>
                        </Token>
                        <Token POSTag="JJ" globalID="58" id="3" offset="293:300">
                            <Text>medical</Text>
                        </Token>
                        <Token POSTag="NN" globalID="59" id="4" offset="301:308">
                            <Text>history</Text>
                        </Token>
                        <Token POSTag="IN" globalID="60" id="5" offset="309:311">
                            <Text>of</Text>
                        </Token>
                        <Token POSTag="JJ" globalID="61" id="6" offset="312:319">
                            <Text>CROHN'S</Text>
                            <METAMAP>[dsyn]</METAMAP>
                            <METAMAP>[dsyn]</METAMAP>
                        </Token>
                        <Token POSTag="NN" globalID="62" id="7" offset="320:327">
                            <Text>DISEASE</Text>
                            <METAMAP>[dsyn]</METAMAP>
                            <METAMAP>[dsyn]</METAMAP>
                            <METAMAP>[dsyn]</METAMAP>
                            <METAMAP>[dsyn]</METAMAP>
                        </Token>
                        <Token POSTag="-LRB-" globalID="63" id="8" offset="327:328">
                            <Text>(</Text>
                            <METAMAP>[dsyn]</METAMAP>
                            <METAMAP>[dsyn]</METAMAP>
                        </Token>
                        <Token POSTag="RB" globalID="64" id="9" offset="328:331">
                            <Text>Not</Text>
                        </Token>
                        <Token POSTag="VBG" globalID="65" id="10" offset="332:342">
                            <Text>Continuing</Text>
                        </Token>
                        <Token POSTag="-RRB-" globalID="66" id="11" offset="342:343">
                            <Text>)</Text>
                        </Token>
                        <Token POSTag="," globalID="67" id="12" offset="343:344">
                            <Text>,</Text>
                        </Token>
                        <Token POSTag="NN" globalID="68" id="13" offset="345:358">
                            <Text>GASTROPARESIS</Text>
                            <METAMAP>[dsyn]</METAMAP>
                        </Token>
                        <Token POSTag="-LRB-" globalID="69" id="14" offset="358:359">
                            <Text>(</Text>
                        </Token>
                        <Token POSTag="RB" globalID="70" id="15" offset="359:362">
                            <Text>Not</Text>
                        </Token>
                        <Token POSTag="VBG" globalID="71" id="16" offset="363:373">
                            <Text>Continuing</Text>
                        </Token>
                        <Token POSTag="-RRB-" globalID="72" id="17" offset="373:374">
                            <Text>)</Text>
                        </Token>
                        <Token POSTag="." globalID="73" id="18" offset="374:375">
                            <Text>.</Text>
                        </Token>
                    </Tokens>
                    <ParseTree>(S1 (S (S (NP (DT The) (NN patient)) (VP (VBD had) (NP (NP (JJ medical) (NN history)) (PP
                        (IN of) (NP (NP (NP (JJ CROHN'S) (NN DISEASE)) (PRN (-LRB- -LRB-) (ADVP (RB Not)) (VP (VBG
                        Continuing)) (-RRB- -RRB-))) (, ,) (NP (NP (NN GASTROPARESIS)) (PRN (-LRB- -LRB-) (ADVP (RB
                        Not)) (VP (VBG Continuing)) (-RRB- -RRB-)))))))) (. .)))
                    </ParseTree>
                </Sentence>
            </Sentences>
        </Paragraph>
        <Paragraph id="3">
            <Sentences Count="1">
                <Sentence id="0" offset="376:381">
                    <Text></Text>
                    <Tokens Count="0"/>
                    <ParseTree/>
                </Sentence>
            </Sentences>
        </Paragraph>
        <Paragraph id="4">
            <Sentences Count="1">
                <Sentence id="0" offset="382:500">
                    <Text>The patient's concomitant medication included MESALAZINE( Unknown, Dosage Form: Unspecified,
                        for CROHN'S DISEASE).
                    </Text>
                    <Tokens Count="19">
                        <Token POSTag="DT" globalID="74" id="0" offset="382:385">
                            <Text>The</Text>
                        </Token>
                        <Token POSTag="JJ" globalID="75" id="1" offset="386:395">
                            <Text>patient's</Text>
                        </Token>
                        <Token POSTag="JJ" globalID="76" id="2" offset="396:407">
                            <Text>concomitant</Text>
                        </Token>
                        <Token POSTag="NN" globalID="77" id="3" offset="408:418">
                            <Text>medication</Text>
                            <METAMAP>[phsu]</METAMAP>
                        </Token>
                        <Token POSTag="VBD" globalID="78" id="4" offset="419:427">
                            <Text>included</Text>
                        </Token>
                        <Token POSTag="NN" globalID="79" id="5" offset="429:439">
                            <Text>MESALAZINE</Text>
                            <METAMAP>[orch,phsu]</METAMAP>
                        </Token>
                        <Token POSTag="-LRB-" globalID="80" id="6" offset="439:440">
                            <Text>(</Text>
                        </Token>
                        <Token POSTag="JJ" globalID="81" id="7" offset="441:448">
                            <Text>Unknown</Text>
                        </Token>
                        <Token POSTag="," globalID="82" id="8" offset="448:449">
                            <Text>,</Text>
                        </Token>
                        <Token POSTag="JJ" globalID="83" id="9" offset="451:457">
                            <Text>Dosage</Text>
                        </Token>
                        <Token POSTag="NN" globalID="84" id="10" offset="458:462">
                            <Text>Form</Text>
                        </Token>
                        <Token POSTag=":" globalID="85" id="11" offset="462:463">
                            <Text>:</Text>
                        </Token>
                        <Token POSTag="NN" globalID="86" id="12" offset="464:475">
                            <Text>Unspecified</Text>
                        </Token>
                        <Token POSTag="," globalID="87" id="13" offset="475:476">
                            <Text>,</Text>
                        </Token>
                        <Token POSTag="IN" globalID="88" id="14" offset="478:481">
                            <Text>for</Text>
                        </Token>
                        <Token POSTag="JJ" globalID="89" id="15" offset="482:489">
                            <Text>CROHN'S</Text>
                            <METAMAP>[dsyn]</METAMAP>
                            <METAMAP>[dsyn]</METAMAP>
                        </Token>
                        <Token POSTag="NN" globalID="90" id="16" offset="490:497">
                            <Text>DISEASE</Text>
                            <METAMAP>[dsyn]</METAMAP>
                            <METAMAP>[dsyn]</METAMAP>
                            <METAMAP>[dsyn]</METAMAP>
                            <METAMAP>[dsyn]</METAMAP>
                        </Token>
                        <Token POSTag="-RRB-" globalID="91" id="17" offset="497:498">
                            <Text>)</Text>
                            <METAMAP>[dsyn]</METAMAP>
                            <METAMAP>[dsyn]</METAMAP>
                        </Token>
                        <Token POSTag="." globalID="92" id="18" offset="498:499">
                            <Text>.</Text>
                        </Token>
                    </Tokens>
                    <ParseTree>(S1 (S (NP (DT The) (JJ patient's) (JJ concomitant) (NN medication)) (VP (VBD included)
                        (NP (NP (NN MESALAZINE)) (PRN (-LRB- -LRB-) (NP (NP (ADJP (ADJP (JJ Unknown)) (, ,) (ADJP (JJ
                        Dosage))) (NN Form)) (: :) (NP (NN Unspecified)) (, ,) (PP (IN for) (NP (JJ CROHN'S) (NN
                        DISEASE)))) (-RRB- -RRB-)))) (. .)))
                    </ParseTree>
                </Sentence>
            </Sentences>
        </Paragraph>
        <Paragraph id="5">
            <Sentences Count="1">
                <Sentence id="0" offset="501:550">
                    <Text>The patient's past medication were unspecified.</Text>
                    <Tokens Count="7">
                        <Token POSTag="DT" globalID="93" id="0" offset="501:504">
                            <Text>The</Text>
                        </Token>
                        <Token POSTag="JJ" globalID="94" id="1" offset="505:514">
                            <Text>patient's</Text>
                        </Token>
                        <Token POSTag="JJ" globalID="95" id="2" offset="515:519">
                            <Text>past</Text>
                        </Token>
                        <Token POSTag="NN" globalID="96" id="3" offset="520:530">
                            <Text>medication</Text>
                        </Token>
                        <Token POSTag="VBD" globalID="97" id="4" offset="531:535">
                            <Text>were</Text>
                        </Token>
                        <Token POSTag="VBN" globalID="98" id="5" offset="536:547">
                            <Text>unspecified</Text>
                        </Token>
                        <Token POSTag="." globalID="99" id="6" offset="547:548">
                            <Text>.</Text>
                        </Token>
                    </Tokens>
                    <ParseTree>(S1 (S (S (NP (DT The) (JJ patient's) (JJ past) (NN medication)) (VP (VBD were) (VP (VBN
                        unspecified)))) (. .)))
                    </ParseTree>
                </Sentence>
            </Sentences>
        </Paragraph>
        <Paragraph id="6">
            <Sentences Count="0"/>
        </Paragraph>
        <Paragraph id="7">
            <Sentences Count="1">
                <Sentence id="0" offset="552:580">
                    <Text>Lab tests were not reported.</Text>
                    <Tokens Count="6">
                        <Token POSTag="NN" globalID="100" id="0" offset="552:555">
                            <Text>Lab</Text>
                        </Token>
                        <Token POSTag="NNS" globalID="101" id="1" offset="556:561">
                            <Text>tests</Text>
                        </Token>
                        <Token POSTag="VBD" globalID="102" id="2" offset="562:566">
                            <Text>were</Text>
                        </Token>
                        <Token POSTag="RB" globalID="103" id="3" offset="567:570">
                            <Text>not</Text>
                        </Token>
                        <Token POSTag="VBN" globalID="104" id="4" offset="571:579">
                            <Text>reported</Text>
                        </Token>
                        <Token POSTag="." globalID="105" id="5" offset="579:580">
                            <Text>.</Text>
                        </Token>
                    </Tokens>
                    <ParseTree>(S1 (S (S (NP (NN Lab) (NNS tests)) (VP (VBD were) (RB not) (VP (VBN reported)))) (.
                        .)))
                    </ParseTree>
                </Sentence>
            </Sentences>
        </Paragraph>
        <Paragraph id="8">
            <Sentences Count="0"/>
        </Paragraph>
        <Paragraph id="9">
            <Sentences Count="1">
                <Sentence id="0" offset="582:690">
                    <Text>This case was considered serious based on the following criteria: (Other Serious (Important
                        Medical Events))
                    </Text>
                    <Tokens Count="20">
                        <Token POSTag="DT" globalID="106" id="0" offset="582:586">
                            <Text>This</Text>
                        </Token>
                        <Token POSTag="NN" globalID="107" id="1" offset="587:591">
                            <Text>case</Text>
                        </Token>
                        <Token POSTag="VBD" globalID="108" id="2" offset="592:595">
                            <Text>was</Text>
                        </Token>
                        <Token POSTag="VBN" globalID="109" id="3" offset="596:606">
                            <Text>considered</Text>
                        </Token>
                        <Token POSTag="JJ" globalID="110" id="4" offset="607:614">
                            <Text>serious</Text>
                        </Token>
                        <Token POSTag="VBN" globalID="111" id="5" offset="615:620">
                            <Text>based</Text>
                        </Token>
                        <Token POSTag="IN" globalID="112" id="6" offset="621:623">
                            <Text>on</Text>
                        </Token>
                        <Token POSTag="DT" globalID="113" id="7" offset="624:627">
                            <Text>the</Text>
                        </Token>
                        <Token POSTag="JJ" globalID="114" id="8" offset="628:637">
                            <Text>following</Text>
                        </Token>
                        <Token POSTag="NNS" globalID="115" id="9" offset="638:646">
                            <Text>criteria</Text>
                        </Token>
                        <Token POSTag=":" globalID="116" id="10" offset="646:647">
                            <Text>:</Text>
                        </Token>
                        <Token POSTag="-LRB-" globalID="117" id="11" offset="648:649">
                            <Text>(</Text>
                        </Token>
                        <Token POSTag="JJ" globalID="118" id="12" offset="649:654">
                            <Text>Other</Text>
                        </Token>
                        <Token POSTag="JJ" globalID="119" id="13" offset="655:662">
                            <Text>Serious</Text>
                        </Token>
                        <Token POSTag="-LRB-" globalID="120" id="14" offset="663:664">
                            <Text>(</Text>
                        </Token>
                        <Token POSTag="JJ" globalID="121" id="15" offset="664:673">
                            <Text>Important</Text>
                        </Token>
                        <Token POSTag="JJ" globalID="122" id="16" offset="674:681">
                            <Text>Medical</Text>
                        </Token>
                        <Token POSTag="NNS" globalID="123" id="17" offset="682:688">
                            <Text>Events</Text>
                        </Token>
                        <Token POSTag="-RRB-" globalID="124" id="18" offset="688:689">
                            <Text>)</Text>
                        </Token>
                        <Token POSTag="-RRB-" globalID="125" id="19" offset="688:689">
                            <Text>)</Text>
                        </Token>
                    </Tokens>
                    <ParseTree>(S1 (S (S (NP (DT This) (NN case)) (VP (VBD was) (VP (VBN considered) (S (ADJP (JJ
                        serious) (PP (VBN based) (PP (IN on) (NP (DT the) (JJ following) (NNS criteria)))))))) (: :))
                        (PRN (-LRB- -LRB-) (NP (NP (JJ Other) (JJ Serious)) (PRN (-LRB- -LRB-) (NP (JJ Important) (JJ
                        Medical) (NNS Events)) (-RRB- -RRB-))) (-RRB- -RRB-))))
                    </ParseTree>
                </Sentence>
            </Sentences>
        </Paragraph>
        <Paragraph id="10">
            <Sentences Count="0"/>
        </Paragraph>
        <Paragraph id="11">
            <Sentences Count="0"/>
        </Paragraph>
    </Paragraphs>
</StartOutput>